MANIFEST.in
setup.py
doom_py/.gitignore
doom_py/CMakeLists.txt
doom_py/README.md
doom_py/__init__.py
doom_py/cmake_all.sh
doom_py/cmake_clean.sh
doom_py/download_freedoom.sh
doom_py/run_cmake.sh
doom_py.egg-info/PKG-INFO
doom_py.egg-info/SOURCES.txt
doom_py.egg-info/dependency_links.txt
doom_py.egg-info/pbr.json
doom_py.egg-info/requires.txt
doom_py.egg-info/top_level.txt
doom_py/cmake_modules/CleanDirectoryList.cmake
doom_py/cmake_modules/CreateLaunchers.cmake
doom_py/cmake_modules/FindFluidSynth.cmake
doom_py/cmake_modules/FindMPG123.cmake
doom_py/cmake_modules/FindNumPy.cmake
doom_py/cmake_modules/FindSDL2.cmake
doom_py/cmake_modules/FindSndFile.cmake
doom_py/cmake_modules/launcher-templates/genericlauncher.cmd.in
doom_py/cmake_modules/launcher-templates/launcher.env.cmd.in
doom_py/cmake_modules/launcher-templates/perconfig.vcproj.user.in
doom_py/cmake_modules/launcher-templates/perconfig.vcxproj.user.in
doom_py/cmake_modules/launcher-templates/targetlauncher.cmd.in
doom_py/cmake_modules/launcher-templates/vcproj.user.in
doom_py/cmake_modules/launcher-templates/vcxproj.user.in
doom_py/examples/bin/vizdoom.so.dir/DependInfo.cmake
doom_py/examples/bin/vizdoom.so.dir/build.make
doom_py/examples/bin/vizdoom.so.dir/cmake_clean.cmake
doom_py/examples/bin/vizdoom.so.dir/depend.make
doom_py/examples/bin/vizdoom.so.dir/flags.make
doom_py/examples/bin/vizdoom.so.dir/progress.make
doom_py/examples/c++/.gitignore
doom_py/examples/c++/Basic.cpp
doom_py/examples/c++/CIG.cpp
doom_py/examples/c++/CIGBots.cpp
doom_py/examples/c++/CIGHost.cpp
doom_py/examples/c++/CMakeLists.txt
doom_py/examples/c++/DeltaButtons.cpp
doom_py/examples/c++/Multiplayer.cpp
doom_py/examples/c++/MultiplayerHost.cpp
doom_py/examples/c++/README.md
doom_py/examples/c++/Seed.cpp
doom_py/examples/c++/Shaping.cpp
doom_py/examples/c++/Spectator.cpp
doom_py/examples/config/basic.cfg
doom_py/examples/config/bots.cfg
doom_py/examples/config/cig.cfg
doom_py/examples/config/deadly_corridor.cfg
doom_py/examples/config/deathmatch.cfg
doom_py/examples/config/defend_the_center.cfg
doom_py/examples/config/defend_the_line.cfg
doom_py/examples/config/health_gathering.cfg
