Metadata-Version: 1.1
Name: doom-py
Version: 0.0.15
Summary: Python bindings to ViZDoom
Home-page: https://github.com/openai/doom-py
Author: OpenAI Community
Author-email: gym@openai.com
License: UNKNOWN
Platform: UNKNOWN
Classifier: License :: OSI Approved :: MIT License
